SSSsnake/__init__.py
SSSsnake-0.0.24.dist-info/LICENSE
SSSsnake-0.0.24.dist-info/METADATA
SSSsnake-0.0.24.dist-info/WHEEL
SSSsnake-0.0.24.dist-info/top_level.txt
SSSsnake-0.0.24.dist-info/RECORD
