Metadata-Version: 2.1
Name: SSSsnake
Version: 0.0.24
Summary: IPythonDisplayTurtles edited for my school's python courses
Home-page: https://github.com/atahan-git/SSSsnake
Author: Atahan Ozturk
Author-email: atahan012000@gmail.com
License: UNKNOWN
Platform: UNKNOWN
Classifier: Framework :: IPython
Classifier: Intended Audience :: Education
Classifier: Programming Language :: Python :: 3
Classifier: License :: OSI Approved :: MIT License
Classifier: Operating System :: OS Independent
Classifier: Topic :: Education
Requires-Python: >=3.6
Requires-Dist: IPython
Requires-Dist: IPythonDisplayTurtle
